vitreaclient/__init__.py
vitreaclient/api.py
vitreaclient/client.py
vitreaclient/constants.py
vitreaclient/constants_backup.py
vitreaclient/constants_broken.py
vitreaclient/__pycache__/__init__.cpython-313.pyc
vitreaclient/__pycache__/api.cpython-313.pyc
vitreaclient/__pycache__/client.cpython-313.pyc
vitreaclient/__pycache__/constants.cpython-313.pyc
vitreaclient-0.2.0.dist-info/licenses/LICENSE
vitreaclient-0.2.0.dist-info/METADATA
vitreaclient-0.2.0.dist-info/WHEEL
vitreaclient-0.2.0.dist-info/top_level.txt
vitreaclient-0.2.0.dist-info/RECORD
