Metadata-Version: 2.4
Name: vitreaclient
Version: 0.2.0
Summary: Python package encapsulating Vitrea box communication protocol.
Author-email: SK <skappdevel@gmail.com>
License: Copyright (c) 2018 The Python Packaging Authority
Project-URL: Homepage, https://github.com/solangek/vitreaclient
Keywords: home automation,vitrea
Classifier: Programming Language :: Python :: 3
Classifier: License :: OSI Approved :: MIT License
Classifier: Operating System :: OS Independent
Requires-Python: >=3.8
License-File: LICENSE
Dynamic: license-file
